lab8/counter_updown.vhd
library IEEE;
use IEEE.STD_LOGIC_1164.ALL ;
use IEEE.NUMERIC_STD.ALL ;
entity COUNTER_UPDOWN is
port (
CLK : in std_logic ;
RST : in std_logic ;    -- Active - high synchronous reset
UP : in std_logic ;     -- '1' = count up , '0' = count down
COUNT : out std_logic_vector (3 downto 0)
) ;
end entity COUNTER_UPDOWN ;
architecture Behavioral of COUNTER_UPDOWN is
signal count_int : unsigned (3 downto 0) := ( others => '0');
begin
process ( CLK )
begin
if rising_edge ( CLK ) then
if RST = '1' then
count_int <= ( others => '0') ;
elsif UP = '1' then
count_int <= count_int + 1;
else
count_int <= count_int - 1;
end if;
end if;
end process;
COUNT <= std_logic_vector ( count_int );
end architecture Behavioral;

lab8/counter_up.vhd
library IEEE;
use IEEE.STD_LOGIC_1164.ALL ;
use IEEE.NUMERIC_STD.ALL ;
entity COUNTER_UP is
port (
CLK : in std_logic;
RST : in std_logic; -- Active - high synchronous reset
COUNT : out std_logic_vector (3 downto 0)
);
end entity COUNTER_UP;
architecture Behavioral of COUNTER_UP is
signal count_int : unsigned (3 downto 0) := ( others => '0');
begin
process ( CLK )
begin
if rising_edge ( CLK ) then
if RST = '1' then
count_int <= ( others => '0') ;
else
count_int <= count_int + 1;
end if;
end if;
end process ;
COUNT <= std_logic_vector ( count_int );
end architecture Behavioral;

lab8/counter_tb.vhd
library IEEE ;
use IEEE.STD_LOGIC_1164.ALL;
entity COUNTER_TB is
end entity COUNTER_TB;
architecture Simulation of COUNTER_TB is
signal CLK : std_logic := '0';
signal RST : std_logic := '0';
signal UP : std_logic := '1';
signal COUNT_UP : std_logic_vector (3 downto 0) ;
signal COUNT_UD : std_logic_vector (3 downto 0) ;
constant CLK_PERIOD : time := 20 ns;
signal sim_running : boolean := true; 
begin
CLK <= not CLK after CLK_PERIOD / 2 when sim_running else CLK;
U1 : entity work.COUNTER_UP
port map ( CLK => CLK , RST => RST , COUNT => COUNT_UP );
U2 : entity work.COUNTER_UPDOWN
port map ( CLK => CLK , RST => RST , UP => UP , COUNT =>COUNT_UD );
STIMULUS : process
begin
-- Reset both counters
RST <= '1'; wait for 40 ns;
RST <= '0';
-- Count up for 10 clock cycles
UP <= '1'; wait for 200 ns;
-- Count down for 5 clock cycles
UP <= '0'; wait for 100 ns;
-- Reset and count up again
RST <= '1'; wait for 40 ns;
RST <= '0'; UP <= '1';
wait for 200 ns;
sim_running <= false; 
wait;
end process;
end architecture Simulation;

lab8/counters.vcd
$date
  Thu Jul 16 12:46:44 2026
$end
$version
  GHDL v0
$end
$timescale
  1 fs
$end
$scope module standard $end
$upscope $end
$scope module std_logic_1164 $end
$upscope $end
$scope module numeric_std $end
$upscope $end
$scope module counter_tb $end
$var reg 1 ! clk $end
$var reg 1 " rst $end
$var reg 1 # up $end
$var reg 4 $ count_up[3:0] $end
$var reg 4 % count_ud[3:0] $end
$var reg 1 & sim_running $end
$scope module u1 $end
$var reg 1 ' clk $end
$var reg 1 ( rst $end
$var reg 4 ) count[3:0] $end
$var reg 4 * count_int[3:0] $end
$upscope $end
$scope module u2 $end
$var reg 1 + clk $end
$var reg 1 , rst $end
$var reg 1 - up $end
$var reg 4 . count[3:0] $end
$var reg 4 / count_int[3:0] $end
$upscope $end
$upscope $end
$enddefinitions $end
#0
0!
1"
1#
b0000 $
b0000 %
1&
0'
1(
b0000 )
b0000 *
0+
1,
1-
b0000 .
b0000 /
#10000000
1!
1'
1+
#20000000
0!
0'
0+
#30000000
1!
1'
1+
#40000000
0!
0"
0'
0(
0+
0,
#50000000
1!
b0001 $
b0001 %
1'
b0001 )
b0001 *
1+
b0001 .
b0001 /
#60000000
0!
0'
0+
#70000000
1!
b0010 $
b0010 %
1'
b0010 )
b0010 *
1+
b0010 .
b0010 /
#80000000
0!
0'
0+
#90000000
1!
b0011 $
b0011 %
1'
b0011 )
b0011 *
1+
b0011 .
b0011 /
#100000000
0!
0'
0+
#110000000
1!
b0100 $
b0100 %
1'
b0100 )
b0100 *
1+
b0100 .
b0100 /
#120000000
0!
0'
0+
#130000000
1!
b0101 $
b0101 %
1'
b0101 )
b0101 *
1+
b0101 .
b0101 /
#140000000
0!
0'
0+
#150000000
1!
b0110 $
b0110 %
1'
b0110 )
b0110 *
1+
b0110 .
b0110 /
#160000000
0!
0'
0+
#170000000
1!
b0111 $
b0111 %
1'
b0111 )
b0111 *
1+
b0111 .
b0111 /
#180000000
0!
0'
0+
#190000000
1!
b1000 $
b1000 %
1'
b1000 )
b1000 *
1+
b1000 .
b1000 /
#200000000
0!
0'
0+
#210000000
1!
b1001 $
b1001 %
1'
b1001 )
b1001 *
1+
b1001 .
b1001 /
#220000000
0!
0'
0+
#230000000
1!
b1010 $
b1010 %
1'
b1010 )
b1010 *
1+
b1010 .
b1010 /
#240000000
0!
0#
0'
0+
0-
#250000000
1!
b1011 $
b1001 %
1'
b1011 )
b1011 *
1+
b1001 .
b1001 /
#260000000
0!
0'
0+
#270000000
1!
b1100 $
b1000 %
1'
b1100 )
b1100 *
1+
b1000 .
b1000 /
#280000000
0!
0'
0+
#290000000
1!
b1101 $
b0111 %
1'
b1101 )
b1101 *
1+
b0111 .
b0111 /
#300000000
0!
0'
0+
#310000000
1!
b1110 $
b0110 %
1'
b1110 )
b1110 *
1+
b0110 .
b0110 /
#320000000
0!
0'
0+
#330000000
1!
b1111 $
b0101 %
1'
b1111 )
b1111 *
1+
b0101 .
b0101 /
#340000000
0!
1"
0'
1(
0+
1,
#350000000
1!
b0000 $
b0000 %
1'
b0000 )
b0000 *
1+
b0000 .
b0000 /
#360000000
0!
0'
0+
#370000000
1!
1'
1+
#380000000
0!
0"
1#
0'
0(
0+
0,
1-
#390000000
1!
b0001 $
b0001 %
1'
b0001 )
b0001 *
1+
b0001 .
b0001 /
#400000000
0!
0'
0+
#410000000
1!
b0010 $
b0010 %
1'
b0010 )
b0010 *
1+
b0010 .
b0010 /
#420000000
0!
0'
0+
#430000000
1!
b0011 $
b0011 %
1'
b0011 )
b0011 *
1+
b0011 .
b0011 /
#440000000
0!
0'
0+
#450000000
1!
b0100 $
b0100 %
1'
b0100 )
b0100 *
1+
b0100 .
b0100 /
#460000000
0!
0'
0+
#470000000
1!
b0101 $
b0101 %
1'
b0101 )
b0101 *
1+
b0101 .
b0101 /
#480000000
0!
0'
0+
#490000000
1!
b0110 $
b0110 %
1'
b0110 )
b0110 *
1+
b0110 .
b0110 /
#500000000
0!
0'
0+
#510000000
1!
b0111 $
b0111 %
1'
b0111 )
b0111 *
1+
b0111 .
b0111 /
#520000000
0!
0'
0+
#530000000
1!
b1000 $
b1000 %
1'
b1000 )
b1000 *
1+
b1000 .
b1000 /
#540000000
0!
0'
0+
#550000000
1!
b1001 $
b1001 %
1'
b1001 )
b1001 *
1+
b1001 .
b1001 /
#560000000
0!
0'
0+
#570000000
1!
b1010 $
b1010 %
1'
b1010 )
b1010 *
1+
b1010 .
b1010 /
#580000000
0!
0&
0'
0+
