LAB6/bcd_to_xs3.vhd
library IEEE;
use IEEE.STD_LOGIC_1164.ALL;
use IEEE.NUMERIC_STD.ALL;

entity BCD_TO_XS3 is
    Port (
        BCD : in  STD_LOGIC_VECTOR(3 downto 0);   -- BCD input (0-9)
        XS3 : out STD_LOGIC_VECTOR(3 downto 0)    -- Excess-3 output
    );
end BCD_TO_XS3;

architecture Behavioral of BCD_TO_XS3 is
begin
    process(BCD)
    begin
        -- Add 3 to the BCD input to get Excess-3
        XS3 <= STD_LOGIC_VECTOR(unsigned(BCD) + 3);
    end process;
end Behavioral;

LAB6/bcd_xs3_tb.vhd
library IEEE;
use IEEE.STD_LOGIC_1164.ALL;

entity BCD_XS3_TB is
end BCD_XS3_TB;

architecture Simulation of BCD_XS3_TB is

    signal BCD : STD_LOGIC_VECTOR(3 downto 0) := "0000";
    signal XS3 : STD_LOGIC_VECTOR(3 downto 0);

begin

    -- Instantiate the Unit Under Test (UUT)
    DUT : entity work.BCD_TO_XS3
        port map (
            BCD => BCD,
            XS3 => XS3
        );

    -- Stimulus Process
    STIMULUS : process
    begin
        BCD <= "0000"; wait for 10 ns; -- 0 -> 0011
        BCD <= "0001"; wait for 10 ns; -- 1 -> 0100
        BCD <= "0010"; wait for 10 ns; -- 2 -> 0101
        BCD <= "0011"; wait for 10 ns; -- 3 -> 0110
        BCD <= "0100"; wait for 10 ns; -- 4 -> 0111
        BCD <= "0101"; wait for 10 ns; -- 5 -> 1000
        BCD <= "0110"; wait for 10 ns; -- 6 -> 1001
        BCD <= "0111"; wait for 10 ns; -- 7 -> 1010
        BCD <= "1000"; wait for 10 ns; -- 8 -> 1011
        BCD <= "1001"; wait for 10 ns; -- 9 -> 1100

        wait;
    end process;

end Simulation;

LAB6/bcd_xs3.vcd
$date
  Thu Jul 02 12:56:25 2026
$end
$version
  GHDL v0
$end
$timescale
  1 fs
$end
$scope module standard $end
$upscope $end
$scope module std_logic_1164 $end
$upscope $end
$scope module numeric_std $end
$upscope $end
$scope module bcd_xs3_tb $end
$var reg 4 ! bcd[3:0] $end
$var reg 4 " xs3[3:0] $end
$scope module dut $end
$var reg 4 # bcd[3:0] $end
$var reg 4 $ xs3[3:0] $end
$upscope $end
$upscope $end
$enddefinitions $end
#0
b0000 !
b0011 "
b0000 #
b0011 $
#10000000
b0001 !
b0100 "
b0001 #
b0100 $
#20000000
b0010 !
b0101 "
b0010 #
b0101 $
#30000000
b0011 !
b0110 "
b0011 #
b0110 $
#40000000
b0100 !
b0111 "
b0100 #
b0111 $
#50000000
b0101 !
b1000 "
b0101 #
b1000 $
#60000000
b0110 !
b1001 "
b0110 #
b1001 $
#70000000
b0111 !
b1010 "
b0111 #
b1010 $
#80000000
b1000 !
b1011 "
b1000 #
b1011 $
#90000000
b1001 !
b1100 "
b1001 #
b1100 $
