LAB6/bin_to_gray.vhd
library IEEE;
use IEEE.STD_LOGIC_1164.ALL;

entity BIN_TO_GRAY is
    Port (
        B : in  STD_LOGIC_VECTOR(3 downto 0);  -- 4-bit binary input
        G : out STD_LOGIC_VECTOR(3 downto 0)   -- 4-bit Gray code output
    );
end BIN_TO_GRAY;

architecture Dataflow of BIN_TO_GRAY is
begin
    G(3) <= B(3);              -- MSB remains the same
    G(2) <= B(3) xor B(2);
    G(1) <= B(2) xor B(1);
    G(0) <= B(1) xor B(0);
end Dataflow;

LAB6/gray_tb.vhd
library IEEE;
use IEEE.STD_LOGIC_1164.ALL;

entity GRAY_TB is
end GRAY_TB;

architecture Simulation of GRAY_TB is

    signal B : STD_LOGIC_VECTOR(3 downto 0) := "0000";
    signal G : STD_LOGIC_VECTOR(3 downto 0);

begin

    -- Instantiate the Unit Under Test (UUT)
    DUT : entity work.BIN_TO_GRAY
        port map (
            B => B,
            G => G
        );

    -- Stimulus Process
    STIMULUS : process
    begin
        B <= "0000"; wait for 10 ns; -- Gray: 0000
        B <= "0001"; wait for 10 ns; -- Gray: 0001
        B <= "0010"; wait for 10 ns; -- Gray: 0011
        B <= "0011"; wait for 10 ns; -- Gray: 0010
        B <= "0100"; wait for 10 ns; -- Gray: 0110
        B <= "0101"; wait for 10 ns; -- Gray: 0111
        B <= "0110"; wait for 10 ns; -- Gray: 0101
        B <= "0111"; wait for 10 ns; -- Gray: 0100
        B <= "1000"; wait for 10 ns; -- Gray: 1100
        B <= "1001"; wait for 10 ns; -- Gray: 1101
        B <= "1010"; wait for 10 ns; -- Gray: 1111
        B <= "1011"; wait for 10 ns; -- Gray: 1110
        B <= "1100"; wait for 10 ns; -- Gray: 1010
        B <= "1101"; wait for 10 ns; -- Gray: 1011
        B <= "1110"; wait for 10 ns; -- Gray: 1001
        B <= "1111"; wait for 10 ns; -- Gray: 1000

        wait;
    end process;

end Simulation;

LAB6/gray.vcd
$date
  Thu Jul 02 13:01:25 2026
$end
$version
  GHDL v0
$end
$timescale
  1 fs
$end
$scope module standard $end
$upscope $end
$scope module std_logic_1164 $end
$upscope $end
$scope module gray_tb $end
$var reg 4 ! b[3:0] $end
$var reg 4 " g[3:0] $end
$scope module dut $end
$var reg 4 # b[3:0] $end
$var reg 4 $ g[3:0] $end
$upscope $end
$upscope $end
$enddefinitions $end
#0
b0000 !
b0000 "
b0000 #
b0000 $
#10000000
b0001 !
b0001 "
b0001 #
b0001 $
#20000000
b0010 !
b0011 "
b0010 #
b0011 $
#30000000
b0011 !
b0010 "
b0011 #
b0010 $
#40000000
b0100 !
b0110 "
b0100 #
b0110 $
#50000000
b0101 !
b0111 "
b0101 #
b0111 $
#60000000
b0110 !
b0101 "
b0110 #
b0101 $
#70000000
b0111 !
b0100 "
b0111 #
b0100 $
#80000000
b1000 !
b1100 "
b1000 #
b1100 $
#90000000
b1001 !
b1101 "
b1001 #
b1101 $
#100000000
b1010 !
b1111 "
b1010 #
b1111 $
#110000000
b1011 !
b1110 "
b1011 #
b1110 $
#120000000
b1100 !
b1010 "
b1100 #
b1010 $
#130000000
b1101 !
b1011 "
b1101 #
b1011 $
#140000000
b1110 !
b1001 "
b1110 #
b1001 $
#150000000
b1111 !
b1000 "
b1111 #
b1000 $
