lab7/t_ff.vhd
library IEEE;
use IEEE.STD_LOGIC_1164.ALL;

entity T_FF is
    Port (
        CLK : in  STD_LOGIC;
        T   : in  STD_LOGIC;
        Q   : out STD_LOGIC;
        QB  : out STD_LOGIC
    );
end entity T_FF;

architecture Behavioral of T_FF is
    signal Q_int : STD_LOGIC := '0';
begin

    process(CLK)
    begin
        if rising_edge(CLK) then
            if T = '1' then
                Q_int <= not Q_int;  -- Toggle
            end if;
        end if;
    end process;

    Q  <= Q_int;
    QB <= not Q_int;

end architecture Behavioral;

lab7/jk_ff.vhd
library IEEE;
use IEEE.STD_LOGIC_1164.ALL;

entity JK_FF is
    Port (
        CLK : in  STD_LOGIC;
        J   : in  STD_LOGIC;
        K   : in  STD_LOGIC;
        Q   : out STD_LOGIC;
        QB  : out STD_LOGIC
    );
end entity JK_FF;

architecture Behavioral of JK_FF is
    signal Q_int : STD_LOGIC := '0';
begin

    process(CLK)
    begin
        if rising_edge(CLK) then
            if J = '0' and K = '0' then
                null;                -- Hold
            elsif J = '0' and K = '1' then
                Q_int <= '0';        -- Reset
            elsif J = '1' and K = '0' then
                Q_int <= '1';        -- Set
            else
                Q_int <= not Q_int;  -- Toggle
            end if;
        end if;
    end process;

    Q  <= Q_int;
    QB <= not Q_int;

end architecture Behavioral;

lab7/d_ff.vhd
library IEEE;
use IEEE.STD_LOGIC_1164.ALL;

entity D_FF is
    Port (
        CLK : in  STD_LOGIC;
        D   : in  STD_LOGIC;
        Q   : out STD_LOGIC;
        QB  : out STD_LOGIC
    );
end entity D_FF;

architecture Behavioral of D_FF is
    signal Q_int : STD_LOGIC := '0';
begin
    process(CLK)
    begin
        if rising_edge(CLK) then
            Q_int <= D;
        end if;
    end process;

    Q  <= Q_int;
    QB <= not Q_int;
end architecture Behavioral;

lab7/sr_ff.vhd
library IEEE;
use IEEE.STD_LOGIC_1164.ALL;

entity SR_FF is
    Port (
        CLK : in  STD_LOGIC;
        S   : in  STD_LOGIC;
        R   : in  STD_LOGIC;
        Q   : out STD_LOGIC;
        QB  : out STD_LOGIC    -- Q complement
    );
end entity SR_FF;

architecture Behavioral of SR_FF is
    signal Q_int : STD_LOGIC := '0';
begin

    process(CLK)
    begin
        if rising_edge(CLK) then
            if S = '0' and R = '0' then
                null;                -- Hold
            elsif S = '0' and R = '1' then
                Q_int <= '0';        -- Reset
            elsif S = '1' and R = '0' then
                Q_int <= '1';        -- Set
            end if;
            -- S='1' and R='1' is forbidden: no assignment
        end if;
    end process;

    Q  <= Q_int;
    QB <= not Q_int;

end architecture Behavioral;

lab7/ff_tb.vhd
library IEEE;
use IEEE.STD_LOGIC_1164.ALL;

entity FF_TB is
end entity FF_TB;

architecture Simulation of FF_TB is

    signal CLK : STD_LOGIC := '0';
    signal S, R : STD_LOGIC := '0';
    signal D : STD_LOGIC := '0';
    signal J, K : STD_LOGIC := '0';
    signal T : STD_LOGIC := '0';

    signal Q_SR, Q_D, Q_JK, Q_T : STD_LOGIC;
    signal QB_SR, QB_D, QB_JK, QB_T : STD_LOGIC;

    constant CLK_PERIOD : time := 10 ns;

begin

    -- Clock Generation Process
    CLK_PROCESS : process
    begin
        while now < 100 ns loop
            CLK <= '0';
            wait for CLK_PERIOD / 2;
            CLK <= '1';
            wait for CLK_PERIOD / 2;
        end loop;
        wait;
    end process;

    -- SR Flip-Flop
    U1 : entity work.SR_FF
        port map (
            CLK => CLK,
            S   => S,
            R   => R,
            Q   => Q_SR,
            QB  => QB_SR
        );

    -- D Flip-Flop
    U2 : entity work.D_FF
        port map (
            CLK => CLK,
            D   => D,
            Q   => Q_D,
            QB  => QB_D
        );

    -- JK Flip-Flop
    U3 : entity work.JK_FF
        port map (
            CLK => CLK,
            J   => J,
            K   => K,
            Q   => Q_JK,
            QB  => QB_JK
        );

    -- T Flip-Flop
    U4 : entity work.T_FF
        port map (
            CLK => CLK,
            T   => T,
            Q   => Q_T,
            QB  => QB_T
        );

    -- Stimulus Process
    STIMULUS : process
    begin

        -- SR Flip-Flop Test
        S <= '1'; R <= '0'; wait for 10 ns;
        S <= '0'; R <= '1'; wait for 10 ns;
        S <= '0'; R <= '0'; wait for 10 ns;

        -- D Flip-Flop Test
        D <= '1'; wait for 10 ns;
        D <= '0'; wait for 10 ns;

        -- JK Flip-Flop Test
        J <= '1'; K <= '0'; wait for 10 ns;
        J <= '1'; K <= '1'; wait for 10 ns;
        J <= '0'; K <= '1'; wait for 10 ns;

        -- T Flip-Flop Test
        T <= '1'; wait for 10 ns;
        T <= '0'; wait for 10 ns;

        assert false report "Simulation finished" severity failure;
    end process;

end architecture Simulation;

lab7/flipflops1.vcd
$date
  Thu Jul 09 13:16:32 2026
$end
$version
  GHDL v0
$end
$timescale
  1 fs
$end
$scope module standard $end
$upscope $end
$scope module std_logic_1164 $end
$upscope $end
$scope module ff_tb $end
$var reg 1 ! clk $end
$var reg 1 " s $end
$var reg 1 # r $end
$var reg 1 $ d $end
$var reg 1 % j $end
$var reg 1 & k $end
$var reg 1 ' t $end
$var reg 1 ( q_sr $end
$var reg 1 ) q_d $end
$var reg 1 * q_jk $end
$var reg 1 + q_t $end
$var reg 1 , qb_sr $end
$var reg 1 - qb_d $end
$var reg 1 . qb_jk $end
$var reg 1 / qb_t $end
$scope module u1 $end
$var reg 1 0 clk $end
$var reg 1 1 s $end
$var reg 1 2 r $end
$var reg 1 3 q $end
$var reg 1 4 qb $end
$var reg 1 5 q_int $end
$upscope $end
$scope module u2 $end
$var reg 1 6 clk $end
$var reg 1 7 d $end
$var reg 1 8 q $end
$var reg 1 9 qb $end
$var reg 1 : q_int $end
$upscope $end
$scope module u3 $end
$var reg 1 ; clk $end
$var reg 1 < j $end
$var reg 1 = k $end
$var reg 1 > q $end
$var reg 1 ? qb $end
$var reg 1 @ q_int $end
$upscope $end
$scope module u4 $end
$var reg 1 A clk $end
$var reg 1 B t $end
$var reg 1 C q $end
$var reg 1 D qb $end
$var reg 1 E q_int $end
$upscope $end
$upscope $end
$enddefinitions $end
#0
0!
1"
0#
0$
0%
0&
0'
0(
0)
0*
0+
1,
1-
1.
1/
00
11
02
03
14
05
06
07
08
19
0:
0;
0<
0=
0>
1?
0@
0A
0B
0C
1D
0E
#5000000
1!
1(
0,
10
13
04
15
16
1;
1A
#10000000
0!
0"
1#
00
01
12
06
0;
0A
#15000000
1!
0(
1,
10
03
14
05
16
1;
1A
#20000000
0!
0#
00
02
06
0;
0A
#25000000
1!
10
16
1;
1A
#30000000
0!
1$
00
06
17
0;
0A
#35000000
1!
1)
0-
10
16
18
09
1:
1;
1A
#40000000
0!
0$
00
06
07
0;
0A
#45000000
1!
0)
1-
10
16
08
19
0:
1;
1A
#50000000
0!
1%
00
06
0;
1<
0A
#55000000
1!
1*
0.
10
16
1;
1>
0?
1@
1A
#60000000
0!
1&
00
06
0;
1=
0A
#65000000
1!
0*
1.
10
16
1;
0>
1?
0@
1A
#70000000
0!
0%
00
06
0;
0<
0A
#75000000
1!
10
16
1;
1A
#80000000
0!
1'
00
06
0;
0A
1B
#85000000
1!
1+
0/
10
16
1;
1A
1C
0D
1E
#90000000
0!
0'
00
06
0;
0A
0B
